fracture_fea_laf/__init__.py
fracture_fea_laf/_version.py
fracture_fea_laf/mesh.py
fracture_fea_laf/plot.py
fracture_fea_laf/postprocess.py
fracture_fea_laf/specimen_geometry.py
fracture_fea_laf/utils.py
fracture_fea_laf/materials/__init__.py
fracture_fea_laf/materials/euromat_A.py
fracture_fea_laf-0.1.1.dist-info/LICENSE
fracture_fea_laf-0.1.1.dist-info/METADATA
fracture_fea_laf-0.1.1.dist-info/WHEEL
fracture_fea_laf-0.1.1.dist-info/top_level.txt
fracture_fea_laf-0.1.1.dist-info/RECORD
