Metadata-Version: 2.1
Name: fracture-fea-laf
Version: 0.1.1
Summary: UNKNOWN
Home-page: UNKNOWN
Author: Maria S. Yankova
Author-email: maria.yankova@manchester.ac.uk
License: MIT license
Project-URL: GitHub, https://github.com/maria-yankova/fracture-fea-laf
Keywords: fea,laf,fracture,materials-science
Platform: UNKNOWN
Classifier: Development Status :: 4 - Beta
Classifier: Intended Audience :: Science/Research
Classifier: Topic :: Scientific/Engineering
Classifier: Operating System :: OS Independent
Classifier: License :: OSI Approved :: MIT License
Classifier: Natural Language :: English
Classifier: Programming Language :: Python :: 3
Classifier: Programming Language :: Python :: 3.6
Classifier: Programming Language :: Python :: 3.7
Classifier: Programming Language :: Python :: 3.8
Requires-Python: >=3.6
Requires-Dist: numpy
Requires-Dist: scipy
Requires-Dist: matplotlib
Requires-Dist: plotly
Requires-Dist: pandas
Requires-Dist: jupyter
Requires-Dist: vecmaths
Requires-Dist: more-itertools
